ccaf_avro_schema_helpers_python_lib/__init__.py
ccaf_avro_schema_helpers_python_lib/generate_flink_sql_statements_for_fully_flatten_root_record.py
ccaf_avro_schema_helpers_python_lib/py.typed
ccaf_avro_schema_helpers_python_lib/swap_camelcase_with_snakecase.py
ccaf_avro_schema_helpers_python_lib/utility.py
ccaf_avro_schema_helpers_python_lib-0.4.2.0.dist-info/METADATA
ccaf_avro_schema_helpers_python_lib-0.4.2.0.dist-info/WHEEL
ccaf_avro_schema_helpers_python_lib-0.4.2.0.dist-info/licenses/LICENSE.md
ccaf_avro_schema_helpers_python_lib-0.4.2.0.dist-info/RECORD
