Metadata-Version: 2.4
Name: ccaf-avro_schema_helpers-python_lib
Version: 0.4.2.0
Summary: CCAF Avro Schema Helpers Python Library
Author-email: "Jeffrey Jonathan Jennings (J3)" <j3@thej3.com>
License-File: LICENSE.md
Requires-Python: >=3.11.9
Requires-Dist: pytest>=8.3.4
